pyfaaster/__init__.py
pyfaaster/__version__.py
pyfaaster/aws/__init__.py
pyfaaster/aws/configuration.py
pyfaaster/aws/dynamodb.py
pyfaaster/aws/exceptions.py
pyfaaster/aws/handlers_decorators.py
pyfaaster/aws/handlers_decorators_v2.py
pyfaaster/aws/kinesis.py
pyfaaster/aws/lambda_helpers.py
pyfaaster/aws/publish.py
pyfaaster/aws/s3_helpers.py
pyfaaster/aws/tools.py
pyfaaster/common/__init__.py
pyfaaster/common/utils.py
pyfaaster-0.2.6.dist-info/LICENSE
pyfaaster-0.2.6.dist-info/METADATA
pyfaaster-0.2.6.dist-info/WHEEL
pyfaaster-0.2.6.dist-info/top_level.txt
pyfaaster-0.2.6.dist-info/RECORD
