Metadata-Version: 2.1
Name: pyfaaster
Version: 0.2.6
Summary: Useful Utilities for Unbelievable AWS Lambdas
Home-page: https://github.com/Cloudzero/pyfaaster
Author: CloudZero
Author-email: support@cloudzero.com
License: BSD
Platform: UNKNOWN
Classifier: License :: OSI Approved :: BSD License
Classifier: Development Status :: 4 - Beta
Classifier: Intended Audience :: Developers
Classifier: Natural Language :: English
Classifier: Programming Language :: Python
Classifier: Programming Language :: Python :: 3
Classifier: Programming Language :: Python :: 3.6
Requires-Dist: boto3 (>=1.14.60)
Requires-Dist: simplejson (>=3.17.2)
Requires-Dist: cachetools (>=4.1.1)
